abero/__init__.py
abero/abero.py
abero/runner.py
abero/version.py
abero-1.0.6.dist-info/LICENSE
abero-1.0.6.dist-info/METADATA
abero-1.0.6.dist-info/WHEEL
abero-1.0.6.dist-info/top_level.txt
abero-1.0.6.dist-info/RECORD
