Metadata-Version: 2.1
Name: abero
Version: 1.0.6
Summary: Analyze multiple files for similarity and/or uniqueness.
Home-page: https://github.com/rmaniego/abero
Author: Rodney Maniego Jr.
Author-email: rod.maniego23@gmail.com
License: MIT
Download-URL: https://github.com/rmaniego/abero/archive/v1.0.tar.gz
Keywords: Python,similarity,diff,compare,files
Platform: UNKNOWN
Classifier: Development Status :: 5 - Production/Stable
Classifier: Intended Audience :: Developers
Classifier: Topic :: Software Development :: Build Tools
Classifier: License :: OSI Approved :: MIT License
Classifier: Programming Language :: Python :: 3
Requires-Python: >=3.6
License-File: LICENSE
Requires-Dist: arkivist
